callosum_dsl/__init__.py
callosum_dsl/core.py
callosum_dsl/templates.py
callosum_dsl-0.2.0.dist-info/METADATA
callosum_dsl-0.2.0.dist-info/WHEEL
callosum_dsl-0.2.0.dist-info/entry_points.txt
callosum_dsl-0.2.0.dist-info/top_level.txt
callosum_dsl-0.2.0.dist-info/RECORD
