Metadata-Version: 2.4
Name: callosum-dsl
Version: 0.2.0
Summary: Python wrapper for Callosum Personality DSL - Create rich, dynamic AI personalities
Author-email: Griffin <griffincancode@gmail.com>
License: MIT
Project-URL: Homepage, https://github.com/griffincancode/callosum
Project-URL: Documentation, https://github.com/griffincancode/callosum/blob/main/docs/README_PYTHON.md
Project-URL: Repository, https://github.com/griffincancode/callosum.git
Project-URL: Issues, https://github.com/griffincancode/callosum/issues
Keywords: ai,personality,dsl,language-model,chatbot,artificial-intelligence,openai,anthropic,llm
Classifier: Development Status :: 4 - Beta
Classifier: Intended Audience :: Developers
Classifier: Topic :: Software Development :: Libraries :: Python Modules
Classifier: Topic :: Scientific/Engineering :: Artificial Intelligence
Classifier: License :: OSI Approved :: MIT License
Classifier: Programming Language :: Python :: 3
Classifier: Programming Language :: Python :: 3.8
Classifier: Programming Language :: Python :: 3.9
Classifier: Programming Language :: Python :: 3.10
Classifier: Programming Language :: Python :: 3.11
Classifier: Programming Language :: Python :: 3.12
Classifier: Operating System :: OS Independent
Requires-Python: >=3.8
Provides-Extra: openai
Requires-Dist: openai>=1.0.0; extra == "openai"
Provides-Extra: anthropic
Requires-Dist: anthropic>=0.7.0; extra == "anthropic"
Provides-Extra: all
Requires-Dist: openai>=1.0.0; extra == "all"
Requires-Dist: anthropic>=0.7.0; extra == "all"
Provides-Extra: dev
Requires-Dist: pytest>=7.0.0; extra == "dev"
Requires-Dist: black>=23.0.0; extra == "dev"
Requires-Dist: mypy>=1.0.0; extra == "dev"
Requires-Dist: twine>=4.0.0; extra == "dev"
Requires-Dist: build>=0.10.0; extra == "dev"
